lefthook/__init__.py
lefthook/__main__.py
lefthook/main.py
lefthook/bin/lefthook-darwin-arm64/lefthook
lefthook/bin/lefthook-darwin-x86_64/lefthook
lefthook/bin/lefthook-freebsd-arm64/lefthook
lefthook/bin/lefthook-freebsd-x86_64/lefthook
lefthook/bin/lefthook-linux-arm64/lefthook
lefthook/bin/lefthook-linux-x86_64/lefthook
lefthook/bin/lefthook-openbsd-arm64/lefthook
lefthook/bin/lefthook-openbsd-x86_64/lefthook
lefthook/bin/lefthook-windows-arm64/lefthook.exe
lefthook/bin/lefthook-windows-x86_64/lefthook.exe
lefthook-2.0.13.dist-info/licenses/LICENSE
lefthook-2.0.13.dist-info/METADATA
lefthook-2.0.13.dist-info/WHEEL
lefthook-2.0.13.dist-info/entry_points.txt
lefthook-2.0.13.dist-info/top_level.txt
lefthook-2.0.13.dist-info/RECORD
